{"is_source_file": false, "format": "", "description": "", "external_files": [], "external_methods": [], "published": [], "classes": [], "methods": [], "calls": [], "search-terms": [], "state": 2, "file_id": 1, "knowledge_revision": 23, "git_revision": "ac0246d42829b6ab26bc5e6f4d2a6e40b1f21e9b", "hash": "d001d53c059625c4bcf75bf5a7f3fcf0", "format-version": 4, "code-base-name": "frontend_react", "filename": "frontend_react/package.json", "revision_history": [{"23": "ac0246d42829b6ab26bc5e6f4d2a6e40b1f21e9b"}]}